jobs_supervisor/FeishuBot.py
jobs_supervisor/__init__.py
jobs_supervisor/jobs_supervisor.py
jobs_supervisor/supervise_jobs.py
jobs_supervisor-0.3.11.dist-info/LICENSE
jobs_supervisor-0.3.11.dist-info/METADATA
jobs_supervisor-0.3.11.dist-info/WHEEL
jobs_supervisor-0.3.11.dist-info/entry_points.txt
jobs_supervisor-0.3.11.dist-info/top_level.txt
jobs_supervisor-0.3.11.dist-info/zip-safe
jobs_supervisor-0.3.11.dist-info/RECORD
