Metadata-Version: 2.1
Name: jobs-supervisor
Version: 0.3.11
Summary: Tools to supervise slurm jobs
License: MIT License
Classifier: License :: OSI Approved :: MIT License
Classifier: Programming Language :: Python :: 3
License-File: LICENSE
Requires-Dist: argparse
Requires-Dist: requests (>=2.27.1)
